flash_kmeans/__init__.py
flash_kmeans/assign_euclid_triton.py
flash_kmeans/centroid_update_triton.py
flash_kmeans/kmeans_triton_impl.py
flash_kmeans-0.1.1.dist-info/licenses/LICENSE.txt
flash_kmeans-0.1.1.dist-info/METADATA
flash_kmeans-0.1.1.dist-info/WHEEL
flash_kmeans-0.1.1.dist-info/top_level.txt
flash_kmeans-0.1.1.dist-info/RECORD
