Metadata-Version: 2.4
Name: flash-kmeans
Version: 0.1.1
Summary: Fast batched K-Means clustering with Triton GPU kernels
Author-email: Shuo Yang <andy_yang@berkeley.edu>
License:                                  Apache License
Project-URL: Homepage, https://github.com/svg-project/flash-kmeans
Project-URL: BugTracker, https://github.com/svg-project/flash-kmeans/issues
Project-URL: Source, https://github.com/svg-project/flash-kmeans
Keywords: kmeans,gpu,triton,clustering,pytorch
Classifier: Programming Language :: Python :: 3
Classifier: License :: OSI Approved :: MIT License
Classifier: Operating System :: OS Independent
Classifier: Topic :: Scientific/Engineering :: Artificial Intelligence
Requires-Python: >=3.8
License-File: LICENSE.txt
Requires-Dist: torch>=2.0
Requires-Dist: triton>=2.0
Requires-Dist: numpy
Requires-Dist: tqdm
Dynamic: license-file
